{"blocks":{"languageVersion":0,"blocks":[{"type":"messagestatus","id":"^RZh{xN?m?:a72YQf]E%","x":230,"y":123,"inputs":{"Power":{"block":{"type":"logic_operation","id":"TZ;/#;J]}(]rht=^xd_o","fields":{"OP":"AND"},"inputs":{"A":{"block":{"type":"logic_compare","id":"Cka),ZOnAY5*+3m,/[-j","fields":{"OP":"EQ"},"inputs":{"A":{"block":{"type":"variables_get","id":"Map{8iR{oK`Y_Gyh/VBd","fields":{"VAR":{"id":"e4_b[O:%a/4}z2wY8YJf"}}}},"B":{"block":{"type":"math_number","id":"9GlOrWdC`8Q`vO*$CgpC","fields":{"NUM":123}}}}}},"B":{"block":{"type":"logic_compare","id":"ZcF~Mb|f2GqROQcMX?yv","fields":{"OP":"EQ"},"inputs":{"A":{"block":{"type":"variables_get_dynamic","id":"J6n^w}aatI6CflQG{$0:","fields":{"VAR":{"id":"~eh_XZ|/rK~Mr%vMJr$6"}}}},"B":{"block":{"type":"math_number","id":"*U9%=~+fA,LQ2ybOL6*|","fields":{"NUM":123}}}}}}}}},"Running":{"block":{"type":"logic_compare","id":"3HI2^4wsnUvEiUw_J,]R","fields":{"OP":"EQ"},"inputs":{"A":{"block":{"type":"variables_get_dynamic","id":"`/^%d?sJCeI}@c219KKn","fields":{"VAR":{"id":"e4_b[O:%a/4}z2wY8YJf"}}}},"B":{"block":{"type":"math_number","id":"l/@cnnl[|ZN/3X0UxP]W","fields":{"NUM":123}}}}}}}}]},"variables":[{"name":"A1","id":"e4_b[O:%a/4}z2wY8YJf"},{"name":"B2","id":"~eh_XZ|/rK~Mr%vMJr$6"}]}